appwee/__init__.py
appwee/app.py
appwee-0.1.1.dist-info/LICENCE.md
appwee-0.1.1.dist-info/METADATA
appwee-0.1.1.dist-info/WHEEL
appwee-0.1.1.dist-info/top_level.txt
appwee-0.1.1.dist-info/RECORD
