Metadata-Version: 2.1
Name: appwee
Version: 0.1.1
Summary: Wrapper around peewee with some QoL features
Author-email: Highghlow <highghlow@proton.me>
Project-URL: Homepage, https://github.com/highghlow/appwee
Project-URL: Bug Tracker, https://github.com/highghlow/appwee/issues
Classifier: Programming Language :: Python :: 3
Classifier: License :: OSI Approved :: MIT License
Classifier: Operating System :: OS Independent
Requires-Python: >=3.7
License-File: LICENCE.md
Requires-Dist: peewee (>=3.16.0)
